backend_shim.py
uvicorn_denial-0.0.0.dist-info/METADATA
uvicorn_denial-0.0.0.dist-info/WHEEL
uvicorn_denial-0.0.0.dist-info/RECORD
