Metadata-Version: 2.1
Name: uvicorn-denial
Version: 0.0.0
Summary: Websocket Denial Response extension for Uvicorn 🔒
Author-email: Marcelo Trylesinski <marcelotryle@gmail.com>
License: MIT
